astrosurveyutils/__init__.py
astrosurveyutils/surveys.py
astrosurveyutils/utils.py
astrosurveyutils/data/dxs-H-DR11_annotated.fits
astrosurveyutils/data/dxs-J-DR11_annotated.fits
astrosurveyutils/data/gcs-H-DR11_annotated.fits
astrosurveyutils/data/gcs-J-DR11_annotated.fits
astrosurveyutils/data/gcs-Y-DR11_annotated.fits
astrosurveyutils/data/gps-H-DR11_annotated.fits
astrosurveyutils/data/gps-J-DR11_annotated.fits
astrosurveyutils/data/gps2-H-DR11_annotated.fits
astrosurveyutils/data/las-H-DR11_annotated.fits
astrosurveyutils/data/las-J-DR11_annotated.fits
astrosurveyutils/data/las-Y-DR11_annotated.fits
astrosurveyutils/data/las2-J-DR11_annotated.fits
astrosurveyutils/data/uds-H-DR11_annotated.fits
astrosurveyutils/data/uds-J-DR11_annotated.fits
astrosurveyutils/data/uhs-J-DR2_annotated.fits
astrosurveyutils/data/vhs-H-DR6_annotated.fits
astrosurveyutils/data/vhs-J-DR6_annotated.fits
astrosurveyutils/data/vhs-Y-DR6_annotated.fits
astrosurveyutils/data/video-H-DR4_annotated.fits
astrosurveyutils/data/video-J-DR4_annotated.fits
astrosurveyutils/data/video-Y-DR4_annotated.fits
astrosurveyutils/data/viking-H-DR5_annotated.fits
astrosurveyutils/data/viking-J-DR5_annotated.fits
astrosurveyutils/data/viking-Y-DR5_annotated.fits
astrosurveyutils/data/vmc-J-DR4_annotated.fits
astrosurveyutils/data/vmc-Y-DR4_annotated.fits
astrosurveyutils/data/vvv-H-DR5_annotated.fits
astrosurveyutils/data/vvv-J-DR5_annotated.fits
astrosurveyutils/data/vvv-Y-DR5_annotated.fits
astrosurveyutils-0.0.1.dist-info/METADATA
astrosurveyutils-0.0.1.dist-info/WHEEL
astrosurveyutils-0.0.1.dist-info/top_level.txt
astrosurveyutils-0.0.1.dist-info/RECORD
